simplepythonwer/__init__.py
simplepythonwer/simplepythonwer.py
test/__init__.py
test/test_wer.py
simplepythonwer-1.0.3.dist-info/LICENSE
simplepythonwer-1.0.3.dist-info/METADATA
simplepythonwer-1.0.3.dist-info/WHEEL
simplepythonwer-1.0.3.dist-info/top_level.txt
simplepythonwer-1.0.3.dist-info/RECORD
