Metadata-Version: 2.1
Name: simplepythonwer
Version: 1.0.3
Summary: A small basic python implementation of WER (word error rate) and levenshtein
Home-page: https://github.com/robmsmt/SimplePythonWER
Author: Rob Smith
Author-email: robmsmt@gmail.com
License: UNKNOWN
Platform: UNKNOWN
Classifier: Programming Language :: Python :: 3
Classifier: License :: OSI Approved :: MIT License
Classifier: Operating System :: OS Independent
